WuyunZhishiku2015211Fix1/README.md
WuyunZhishiku2015211Fix1/__init__.py
WuyunZhishiku2015211Fix1/__main__.py
WuyunZhishiku2015211Fix1/file.epub
WuyunZhishiku2015211Fix1/index.html
WuyunZhishiku2015211Fix1/css/__init__.py
WuyunZhishiku2015211Fix1/css/annotations.css
WuyunZhishiku2015211Fix1/css/main.css
WuyunZhishiku2015211Fix1/css/normalize.css
WuyunZhishiku2015211Fix1/css/popup.css
WuyunZhishiku2015211Fix1/font/__init__.py
WuyunZhishiku2015211Fix1/font/fontello.eot
WuyunZhishiku2015211Fix1/font/fontello.svg
WuyunZhishiku2015211Fix1/font/fontello.ttf
WuyunZhishiku2015211Fix1/font/fontello.woff
WuyunZhishiku2015211Fix1/img/__init__.py
WuyunZhishiku2015211Fix1/img/annotator-glyph-sprite.png
WuyunZhishiku2015211Fix1/img/annotator-icon-sprite.png
WuyunZhishiku2015211Fix1/img/apple-touch-icon.png
WuyunZhishiku2015211Fix1/img/cancelfullscreen.png
WuyunZhishiku2015211Fix1/img/close.png
WuyunZhishiku2015211Fix1/img/fullscreen.png
WuyunZhishiku2015211Fix1/img/loader.gif
WuyunZhishiku2015211Fix1/img/menu-icon.png
WuyunZhishiku2015211Fix1/img/save.png
WuyunZhishiku2015211Fix1/img/saved.png
WuyunZhishiku2015211Fix1/img/settings-s.png
WuyunZhishiku2015211Fix1/img/settings.png
WuyunZhishiku2015211Fix1/img/star.png
WuyunZhishiku2015211Fix1/js/__init__.py
WuyunZhishiku2015211Fix1/js/epub.js
WuyunZhishiku2015211Fix1/js/epub.min.js
WuyunZhishiku2015211Fix1/js/epub.min.map
WuyunZhishiku2015211Fix1/js/hooks.min.js
WuyunZhishiku2015211Fix1/js/hooks.min.map
WuyunZhishiku2015211Fix1/js/reader.js
WuyunZhishiku2015211Fix1/js/reader.js.map
WuyunZhishiku2015211Fix1/js/reader.min.js
WuyunZhishiku2015211Fix1/js/reader.min.map
WuyunZhishiku2015211Fix1/js/hooks/__init__.py
WuyunZhishiku2015211Fix1/js/hooks/extensions/__init__.py
WuyunZhishiku2015211Fix1/js/hooks/extensions/highlight.js
WuyunZhishiku2015211Fix1/js/libs/__init__.py
WuyunZhishiku2015211Fix1/js/libs/jquery.min.js
WuyunZhishiku2015211Fix1/js/libs/localforage.min.js
WuyunZhishiku2015211Fix1/js/libs/screenfull.js
wuyun_zhishiku_2015_2_11_fix1-2024.3.2.0.dist-info/METADATA
wuyun_zhishiku_2015_2_11_fix1-2024.3.2.0.dist-info/WHEEL
wuyun_zhishiku_2015_2_11_fix1-2024.3.2.0.dist-info/entry_points.txt
wuyun_zhishiku_2015_2_11_fix1-2024.3.2.0.dist-info/top_level.txt
wuyun_zhishiku_2015_2_11_fix1-2024.3.2.0.dist-info/RECORD
